README.rst
delfick_error.py
delfick_error_pytest.py
setup.py
delfick_error.egg-info/PKG-INFO
delfick_error.egg-info/SOURCES.txt
delfick_error.egg-info/dependency_links.txt
delfick_error.egg-info/entry_points.txt
delfick_error.egg-info/requires.txt
delfick_error.egg-info/top_level.txt