Metadata-Version: 2.1
Name: delfick-error
Version: 1.8
Summary: Customized Exception class
Home-page: http://github.com/delfick/delfick_error
Author: Stephen Moore
Author-email: stephen@delfick.com
License: MIT
Keywords: exception
Platform: UNKNOWN
Provides-Extra: tests
